Metadata-Version: 1.0
Name: pagespeedwrapper
Version: 0.1.1
Summary: Easily get Google PageSpeed results
Home-page: UNKNOWN
Author: Peter W
Author-email: peter@svrrack.com
License: MIT
Platform: UNKNOWN
